{
    "code": "200",
    "message": "success!",
    "repeatToken": null,
    "result": [
        {
            "categoryName": "男装",
            "skuniCode": "501_501100_10100",
            "productId": 501,
            "productName": "Tee",
            "skuList": [
                {
                    "skuniCode": "501_501100_10100",
                    "name": "白"
                },
                {
                    "skuniCode": "501_501107_10100",
                    "name": "黑"
                },
                {
                    "skuniCode": "501_501223_10100",
                    "name": "玉米丝色"
                },
                {
                    "skuniCode": "501_501230_10100",
                    "name": "雏菊色"
                },
                {
                    "skuniCode": "501_501237_10100",
                    "name": "浅蓝色"
                },
                {
                    "skuniCode": "501_501244_10100",
                    "name": "海利康花色"
                },
                {
                    "skuniCode": "501_501251_10100",
                    "name": "橙色"
                },
                {
                    "skuniCode": "501_501258_10100",
                    "name": "浅粉"
                },
                {
                    "skuniCode": "501_501265_10100",
                    "name": "浅绿色"
                },
                {
                    "skuniCode": "501_501272_10100",
                    "name": "红色"
                },
                {
                    "skuniCode": "501_501279_10100",
                    "name": "宝石蓝"
                },
                {
                    "skuniCode": "501_501286_10100",
                    "name": "栗色"
                },
                {
                    "skuniCode": "501_501293_10100",
                    "name": "炭色"
                },
                {
                    "skuniCode": "501_501300_10100",
                    "name": "卡罗莱纳蓝"
                },
                {
                    "skuniCode": "501_501307_10100",
                    "name": "爱尔兰绿"
                },
                {
                    "skuniCode": "501_501216_10100",
                    "name": "紫"
                },
                {
                    "skuniCode": "501_501314_10100",
                    "name": "兰花紫"
                },
                {
                    "skuniCode": "501_501121_10100",
                    "name": "藏青"
                },
                {
                    "skuniCode": "501_501321_10100",
                    "name": "RS运动灰色"
                },
                {
                    "skuniCode": "501_501328_10101",
                    "name": "深巧克力色"
                },
                {
                    "skuniCode": "501_501335_10101",
                    "name": "军绿色"
                },
                {
                    "skuniCode": "501_501342_10101",
                    "name": "翡翠色"
                },
                {
                    "skuniCode": "501_501349_10101",
                    "name": "森林绿"
                },
                {
                    "skuniCode": "501_501356_10101",
                    "name": "沙色"
                },
                {
                    "skuniCode": "501_501198_10101",
                    "name": "深麻灰"
                },
                {
                    "skuniCode": "501_501363_10101",
                    "name": "麻灰红"
                },
                {
                    "skuniCode": "501_501370_10101",
                    "name": "麻灰紫"
                },
                {
                    "skuniCode": "501_501377_10101",
                    "name": "杜鵑花色"
                },
                {
                    "skuniCode": "501_501384_10101",
                    "name": "麻灰宝蓝色"
                },
                {
                    "skuniCode": "501_501391_10101",
                    "name": "麻灰爱尔兰绿"
                },
                {
                    "skuniCode": "501_501398_10101",
                    "name": "钴蓝色"
                },
                {
                    "skuniCode": "501_501405_10101",
                    "name": "金色"
                },
                {
                    "skuniCode": "501_501412_10101",
                    "name": "荧光橙色"
                },
                {
                    "skuniCode": "501_501419_10101",
                    "name": "荧光粉色"
                },
                {
                    "skuniCode": "501_501426_10101",
                    "name": "荧光绿"
                },
                {
                    "skuniCode": "501_501115_10102",
                    "name": "麻棉灰色"
                },
                {
                    "skuniCode": "501_501179_10102",
                    "name": "麻棉米色"
                },
                {
                    "skuniCode": "501_501217_10102",
                    "name": "迷彩灰"
                }
            ]
        },
        {
            "categoryName": "男装",
            "skuniCode": "581_581100_10100",
            "productId": 581,
            "productName": "Polo衫",
            "skuList": [
                {
                    "skuniCode": "581_581100_10100",
                    "name": "白"
                },
                {
                    "skuniCode": "581_581107_10100",
                    "name": "黑"
                },
                {
                    "skuniCode": "581_581280_10100",
                    "name": "麻灰"
                },
                {
                    "skuniCode": "581_581282_10100",
                    "name": "玫红"
                },
                {
                    "skuniCode": "581_581283_10100",
                    "name": "浅粉"
                },
                {
                    "skuniCode": "581_581284_10100",
                    "name": "深玫红"
                },
                {
                    "skuniCode": "581_581268_10100",
                    "name": "粉色"
                },
                {
                    "skuniCode": "581_581267_10100",
                    "name": "酒红"
                },
                {
                    "skuniCode": "581_581271_10100",
                    "name": "大红"
                },
                {
                    "skuniCode": "581_581269_10100",
                    "name": "黄色"
                },
                {
                    "skuniCode": "581_581285_10100",
                    "name": "橙黄"
                },
                {
                    "skuniCode": "581_581286_10100",
                    "name": "香蕉黄"
                },
                {
                    "skuniCode": "581_581287_10100",
                    "name": "墨绿"
                },
                {
                    "skuniCode": "581_581288_10100",
                    "name": "艾绿"
                },
                {
                    "skuniCode": "581_581289_10100",
                    "name": "明绿"
                },
                {
                    "skuniCode": "581_581290_10100",
                    "name": "正绿"
                },
                {
                    "skuniCode": "581_581291_10100",
                    "name": "深紫"
                },
                {
                    "skuniCode": "581_581272_10100",
                    "name": "湖蓝"
                },
                {
                    "skuniCode": "581_581292_10100",
                    "name": "天蓝"
                },
                {
                    "skuniCode": "581_581273_10100",
                    "name": "宝蓝"
                },
                {
                    "skuniCode": "581_581266_10100",
                    "name": "藏青"
                },
                {
                    "skuniCode": "581_581274_10100",
                    "name": "咖啡色"
                }
            ]
        },
        {
            "categoryName": "男装",
            "skuniCode": "8001_8001100_10100",
            "productId": 8001,
            "productName": "套头卫衣",
            "skuList": [
                {
                    "skuniCode": "8001_8001100_10100",
                    "name": "白"
                },
                {
                    "skuniCode": "8001_8001107_10100",
                    "name": "黑"
                },
                {
                    "skuniCode": "8001_8001140_10100",
                    "name": "炭黑"
                },
                {
                    "skuniCode": "8001_8001200_10100",
                    "name": "麻灰"
                },
                {
                    "skuniCode": "8001_8001146_10100",
                    "name": "酒红"
                },
                {
                    "skuniCode": "8001_8001152_10100",
                    "name": "大红"
                },
                {
                    "skuniCode": "8001_8001158_10100",
                    "name": "深玫红"
                },
                {
                    "skuniCode": "8001_8001164_10100",
                    "name": "香蕉黄"
                },
                {
                    "skuniCode": "8001_8001170_10100",
                    "name": "橙黄"
                },
                {
                    "skuniCode": "8001_8001182_10100",
                    "name": "深藏青"
                },
                {
                    "skuniCode": "8001_8001176_10100",
                    "name": "藏青"
                },
                {
                    "skuniCode": "8001_8001188_10100",
                    "name": "湖蓝"
                },
                {
                    "skuniCode": "8001_8001194_10100",
                    "name": "宝蓝"
                },
                {
                    "skuniCode": "8001_8001135_10103",
                    "name": "粉色"
                }
            ]
        },
        {
            "categoryName": "男装",
            "skuniCode": "8011_8011100_10100",
            "productId": 8011,
            "productName": "连帽卫衣",
            "skuList": [
                {
                    "skuniCode": "8011_8011100_10100",
                    "name": "白"
                },
                {
                    "skuniCode": "8011_8011107_10100",
                    "name": "黑"
                },
                {
                    "skuniCode": "8011_8011132_10100",
                    "name": "炭黑"
                },
                {
                    "skuniCode": "8011_8011196_10100",
                    "name": "麻灰"
                },
                {
                    "skuniCode": "8011_8011138_10100",
                    "name": "酒红"
                },
                {
                    "skuniCode": "8011_8011144_10100",
                    "name": "大红"
                },
                {
                    "skuniCode": "8011_8011150_10100",
                    "name": "深玫红"
                },
                {
                    "skuniCode": "8011_8011162_10100",
                    "name": "香蕉黄"
                },
                {
                    "skuniCode": "8011_8011156_10100",
                    "name": "橙黄"
                },
                {
                    "skuniCode": "8011_8011180_10100",
                    "name": "深藏青"
                },
                {
                    "skuniCode": "8011_8011168_10100",
                    "name": "湖蓝"
                },
                {
                    "skuniCode": "8011_8011174_10100",
                    "name": "宝蓝"
                },
                {
                    "skuniCode": "8011_8011186_10100",
                    "name": "藏青"
                }
            ]
        },
        {
            "categoryName": "男装",
            "skuniCode": "8021_8021101_10100",
            "productId": 8021,
            "productName": "连帽拉链卫衣",
            "skuList": [
                {
                    "skuniCode": "8021_8021101_10100",
                    "name": "白"
                },
                {
                    "skuniCode": "8021_8021109_10100",
                    "name": "黑"
                },
                {
                    "skuniCode": "8021_8021124_10100",
                    "name": "炭黑"
                },
                {
                    "skuniCode": "8021_8021188_10100",
                    "name": "麻灰"
                },
                {
                    "skuniCode": "8021_8021130_10100",
                    "name": "酒红"
                },
                {
                    "skuniCode": "8021_8021136_10100",
                    "name": "大红"
                },
                {
                    "skuniCode": "8021_8021142_10100",
                    "name": "深玫红"
                },
                {
                    "skuniCode": "8021_8021148_10100",
                    "name": "橙黄"
                },
                {
                    "skuniCode": "8021_8021154_10100",
                    "name": "香蕉黄"
                },
                {
                    "skuniCode": "8021_8021160_10100",
                    "name": "湖蓝"
                },
                {
                    "skuniCode": "8021_8021166_10100",
                    "name": "藏青"
                },
                {
                    "skuniCode": "8021_8021172_10100",
                    "name": "深藏青"
                },
                {
                    "skuniCode": "8021_8021178_10100",
                    "name": "宝蓝"
                }
            ]
        },
        {
            "categoryName": "男装",
            "skuniCode": "3551_3551100_10103",
            "productId": 3551,
            "productName": "衬衫",
            "skuList": [
                {
                    "skuniCode": "3551_3551100_10103",
                    "name": "白"
                },
                {
                    "skuniCode": "3551_3551105_10103",
                    "name": "黑"
                }
            ]
        },
        {
            "categoryName": "男装",
            "skuniCode": "3531_3531110_0",
            "productId": 3531,
            "productName": "拉链衬衫",
            "skuList": [
                {
                    "skuniCode": "3531_3531110_0",
                    "name": "白"
                },
                {
                    "skuniCode": "3531_3531100_0",
                    "name": "黑"
                }
            ]
        },
        {
            "categoryName": "女装",
            "skuniCode": "10001_10001100_10103",
            "productId": 10001,
            "productName": "Tee",
            "skuList": [
                {
                    "skuniCode": "10001_10001100_10103",
                    "name": "白"
                },
                {
                    "skuniCode": "10001_10001107_10103",
                    "name": "黑"
                },
                {
                    "skuniCode": "10001_10001121_10103",
                    "name": "藏青"
                },
                {
                    "skuniCode": "10001_10001114_10103",
                    "name": "麻棉灰色"
                },
                {
                    "skuniCode": "10001_10001179_10103",
                    "name": "麻棉米色"
                }
            ]
        },
        {
            "categoryName": "女装",
            "skuniCode": "10031_10031102_0",
            "productId": 10031,
            "productName": "短Tee",
            "skuList": [
                {
                    "skuniCode": "10031_10031102_0",
                    "name": "白"
                },
                {
                    "skuniCode": "10031_10031109_0",
                    "name": "黑"
                }
            ]
        },
        {
            "categoryName": "女装",
            "skuniCode": "10041_10041102_0",
            "productId": 10041,
            "productName": "中长宽松Tee",
            "skuList": [
                {
                    "skuniCode": "10041_10041102_0",
                    "name": "白"
                },
                {
                    "skuniCode": "10041_10041106_0",
                    "name": "黑"
                }
            ]
        },
        {
            "categoryName": "女装",
            "skuniCode": "10081_10081100_0",
            "productId": 10081,
            "productName": "流苏下摆中长Tee",
            "skuList": [
                {
                    "skuniCode": "10081_10081100_0",
                    "name": "白"
                },
                {
                    "skuniCode": "10081_10081104_0",
                    "name": "黑"
                }
            ]
        },
        {
            "categoryName": "女装",
            "skuniCode": "10025_10025101_10103",
            "productId": 10025,
            "productName": "Polo衫",
            "skuList": [
                {
                    "skuniCode": "10025_10025101_10103",
                    "name": "白"
                },
                {
                    "skuniCode": "10025_10025107_10103",
                    "name": "黑"
                },
                {
                    "skuniCode": "10025_10025124_10103",
                    "name": "麻灰"
                }
            ]
        },
        {
            "categoryName": "女装",
            "skuniCode": "15013_15013100_10103",
            "productId": 15013,
            "productName": "套头落肩卫衣",
            "skuList": [
                {
                    "skuniCode": "15013_15013100_10103",
                    "name": "白"
                },
                {
                    "skuniCode": "15013_15013103_10103",
                    "name": "黑"
                },
                {
                    "skuniCode": "15013_15013106_10103",
                    "name": "麻灰"
                },
                {
                    "skuniCode": "15013_15013109_10103",
                    "name": "粉色"
                }
            ]
        },
        {
            "categoryName": "女装",
            "skuniCode": "8029_8029101_10103",
            "productId": 8029,
            "productName": "连帽卫衣",
            "skuList": [
                {
                    "skuniCode": "8029_8029101_10103",
                    "name": "白"
                },
                {
                    "skuniCode": "8029_8029127_10103",
                    "name": "黑"
                },
                {
                    "skuniCode": "8029_8029132_10103",
                    "name": "麻灰"
                }
            ]
        },
        {
            "categoryName": "女装",
            "skuniCode": "16013_16013103_10103",
            "productId": 16013,
            "productName": "连帽拉链卫衣",
            "skuList": [
                {
                    "skuniCode": "16013_16013103_10103",
                    "name": "白"
                },
                {
                    "skuniCode": "16013_16013111_10103",
                    "name": "黑"
                },
                {
                    "skuniCode": "16013_16013124_10103",
                    "name": "麻灰"
                }
            ]
        },
        {
            "categoryName": "女装",
            "skuniCode": "16021_16021100_10103",
            "productId": 16021,
            "productName": "中长卫衣",
            "skuList": [
                {
                    "skuniCode": "16021_16021100_10103",
                    "name": "白"
                },
                {
                    "skuniCode": "16021_16021105_10103",
                    "name": "黑"
                }
            ]
        },
        {
            "categoryName": "女装",
            "skuniCode": "15053_15053101_10103",
            "productId": 15053,
            "productName": "连帽短卫衣",
            "skuList": [
                {
                    "skuniCode": "15053_15053101_10103",
                    "name": "白"
                },
                {
                    "skuniCode": "15053_15053106_10103",
                    "name": "黑"
                }
            ]
        },
        {
            "categoryName": "女装",
            "skuniCode": "17000_17000105_10103",
            "productId": 17000,
            "productName": "包臀裙",
            "skuList": [
                {
                    "skuniCode": "17000_17000105_10103",
                    "name": "白"
                }
            ]
        },
        {
            "categoryName": "女装",
            "skuniCode": "17001_17001110_10103",
            "productId": 17001,
            "productName": "小A裙",
            "skuList": [
                {
                    "skuniCode": "17001_17001110_10103",
                    "name": "白"
                }
            ]
        },
        {
            "categoryName": "儿童家庭",
            "skuniCode": "530_530102_10103",
            "productId": 530,
            "productName": "儿童Tee",
            "skuList": [
                {
                    "skuniCode": "530_530102_10103",
                    "name": "白"
                },
                {
                    "skuniCode": "530_530112_10103",
                    "name": "黑"
                },
                {
                    "skuniCode": "530_530142_10103",
                    "name": "藏青"
                },
                {
                    "skuniCode": "530_530236_10103",
                    "name": "麻棉灰色"
                },
                {
                    "skuniCode": "530_530192_10103",
                    "name": "麻棉米色"
                },
                {
                    "skuniCode": "530_530244_10103",
                    "name": "迷彩灰"
                }
            ]
        },
        {
            "categoryName": "儿童家庭",
            "skuniCode": "535_535102_10100",
            "productId": 535,
            "productName": "套头卫衣",
            "skuList": [
                {
                    "skuniCode": "535_535102_10100",
                    "name": "白"
                },
                {
                    "skuniCode": "535_535108_10100",
                    "name": "黑"
                },
                {
                    "skuniCode": "535_535132_10100",
                    "name": "炭黑"
                },
                {
                    "skuniCode": "535_535196_10100",
                    "name": "麻灰"
                },
                {
                    "skuniCode": "535_535138_10100",
                    "name": "酒红"
                },
                {
                    "skuniCode": "535_535144_10100",
                    "name": "大红"
                },
                {
                    "skuniCode": "535_535150_10100",
                    "name": "深玫红"
                },
                {
                    "skuniCode": "535_535156_10100",
                    "name": "香蕉黄"
                },
                {
                    "skuniCode": "535_535162_10100",
                    "name": "橙黄"
                },
                {
                    "skuniCode": "535_535168_10100",
                    "name": "深藏青"
                },
                {
                    "skuniCode": "535_535174_10100",
                    "name": "藏青"
                },
                {
                    "skuniCode": "535_535180_10100",
                    "name": "湖蓝"
                },
                {
                    "skuniCode": "535_535186_10100",
                    "name": "宝蓝"
                },
                {
                    "skuniCode": "535_535192_10103",
                    "name": "粉色"
                }
            ]
        },
        {
            "categoryName": "儿童家庭",
            "skuniCode": "547_547102_10100",
            "productId": 547,
            "productName": "连帽卫衣",
            "skuList": [
                {
                    "skuniCode": "547_547102_10100",
                    "name": "白"
                },
                {
                    "skuniCode": "547_547178_10100",
                    "name": "黑"
                },
                {
                    "skuniCode": "547_547186_10100",
                    "name": "炭黑"
                },
                {
                    "skuniCode": "547_547250_10100",
                    "name": "麻灰"
                },
                {
                    "skuniCode": "547_547198_10100",
                    "name": "酒红"
                },
                {
                    "skuniCode": "547_547204_10100",
                    "name": "大红"
                },
                {
                    "skuniCode": "547_547210_10100",
                    "name": "深玫红"
                },
                {
                    "skuniCode": "547_547216_10100",
                    "name": "香蕉黄"
                },
                {
                    "skuniCode": "547_547222_10100",
                    "name": "橙黄"
                },
                {
                    "skuniCode": "547_547228_10100",
                    "name": "深藏青"
                },
                {
                    "skuniCode": "547_547234_10100",
                    "name": "藏青"
                },
                {
                    "skuniCode": "547_547240_10100",
                    "name": "湖蓝"
                },
                {
                    "skuniCode": "547_547246_10100",
                    "name": "宝蓝"
                }
            ]
        },
        {
            "categoryName": "儿童家庭",
            "skuniCode": "45001_0_0",
            "productId": 45001,
            "productName": "婴儿口水兜",
            "skuList": [
                {
                    "skuniCode": "45001_0_0",
                    "name": "婴儿口水兜"
                }
            ]
        },
        {
            "categoryName": "儿童家庭",
            "skuniCode": "45011_45011112_0",
            "productId": 45011,
            "productName": "婴儿连体衫",
            "skuList": [
                {
                    "skuniCode": "45011_45011112_0",
                    "name": "白"
                }
            ]
        },
        {
            "categoryName": "配饰",
            "skuniCode": "50011_50011103_10100",
            "productId": 50011,
            "productName": "帆布袋",
            "skuList": [
                {
                    "skuniCode": "50011_50011103_10100",
                    "name": "白"
                }
            ]
        },
        {
            "categoryName": "配饰",
            "skuniCode": "55001_55001101_0",
            "productId": 55001,
            "productName": "丝巾 ",
            "skuList": [
                {
                    "skuniCode": "55001_55001101_0",
                    "name": "45cmx45cm"
                },
                {
                    "skuniCode": "55001_55001102_0",
                    "name": "90cmx90cm"
                }
            ]
        },
        {
            "categoryName": "配饰",
            "skuniCode": "55033_0_0",
            "productId": 55033,
            "productName": "发带",
            "skuList": [
                {
                    "skuniCode": "55033_0_0",
                    "name": "发带"
                }
            ]
        },
        {
            "categoryName": "潮品",
            "skuniCode": "80001_80001106_10104",
            "productId": 80001,
            "productName": "苹果手机壳 ",
            "skuList": [
                {
                    "skuniCode": "80001_80001106_10104",
                    "name": "iPhone6"
                },
                {
                    "skuniCode": "80001_80001108_10104",
                    "name": "iPhone7"
                }
            ]
        },
        {
            "categoryName": "潮品",
            "skuniCode": "80051_80051100_10104",
            "productId": 80051,
            "productName": "华为手机壳",
            "skuList": [
                {
                    "skuniCode": "80051_80051100_10104",
                    "name": "华为P10"
                },
                {
                    "skuniCode": "80051_80051101_10104",
                    "name": "华为p10plus"
                },
                {
                    "skuniCode": "80051_80051102_10104",
                    "name": "华为mate9"
                }
            ]
        },
        {
            "categoryName": "潮品",
            "skuniCode": "80251_80251100_10104",
            "productId": 80251,
            "productName": "VIVO手机壳",
            "skuList": [
                {
                    "skuniCode": "80251_80251100_10104",
                    "name": "Vivo X9"
                },
                {
                    "skuniCode": "80251_80251101_10104",
                    "name": "Vivo X9plus"
                },
                {
                    "skuniCode": "80251_80251102_10104",
                    "name": "Vivo X play6"
                }
            ]
        },
        {
            "categoryName": "潮品",
            "skuniCode": "80151_80151100_10104",
            "productId": 80151,
            "productName": "OPPO手机壳",
            "skuList": [
                {
                    "skuniCode": "80151_80151100_10104",
                    "name": "Oppo R9"
                },
                {
                    "skuniCode": "80151_80151101_10104",
                    "name": "Oppo R9s"
                },
                {
                    "skuniCode": "80151_80151102_10104",
                    "name": "Oppo R9plus"
                },
                {
                    "skuniCode": "80151_80151103_10104",
                    "name": "Oppo R9splus"
                }
            ]
        },
        {
            "categoryName": "潮品",
            "skuniCode": "87401_87401102_0",
            "productId": 87401,
            "productName": "鼠标垫",
            "skuList": [
                {
                    "skuniCode": "87401_87401102_0",
                    "name": "30cmX25cm"
                }
            ]
        },
        {
            "categoryName": "潮品",
            "skuniCode": "87405_87405100_0",
            "productId": 87405,
            "productName": "桌垫",
            "skuList": [
                {
                    "skuniCode": "87405_87405100_0",
                    "name": "90cmx40cm"
                }
            ]
        },
        {
            "categoryName": "娱乐",
            "skuniCode": "84251_0_0",
            "productId": 84251,
            "productName": "拼图",
            "skuList": [
                {
                    "skuniCode": "84251_0_0",
                    "name": "拼图"
                }
            ]
        },
        {
            "categoryName": "娱乐",
            "skuniCode": "85321_0_0",
            "productId": 85321,
            "productName": "飞镖盘",
            "skuList": [
                {
                    "skuniCode": "85321_0_0",
                    "name": "飞镖盘"
                }
            ]
        },
        {
            "categoryName": "娱乐",
            "skuniCode": "86012_0_0",
            "productId": 86012,
            "productName": "魔方",
            "skuList": [
                {
                    "skuniCode": "86012_0_0",
                    "name": "魔方"
                }
            ]
        },
        {
            "categoryName": "家居",
            "skuniCode": "70001_70001101_0",
            "productId": 70001,
            "productName": "抱枕 ",
            "skuList": [
                {
                    "skuniCode": "70001_70001101_0",
                    "name": "42cm"
                },
                {
                    "skuniCode": "70001_70001102_0",
                    "name": "50cm"
                },
                {
                    "skuniCode": "70001_0_0",
                    "name": "抱枕 "
                }
            ]
        },
        {
            "categoryName": "家居",
            "skuniCode": "70005_70005100_0",
            "productId": 70005,
            "productName": "坐垫",
            "skuList": [
                {
                    "skuniCode": "70005_70005100_0",
                    "name": "46cmx46cm"
                }
            ]
        },
        {
            "categoryName": "家居",
            "skuniCode": "70010_70010100_0",
            "productId": 70010,
            "productName": "枕套",
            "skuList": [
                {
                    "skuniCode": "70010_70010100_0",
                    "name": "75cmx50cm"
                }
            ]
        },
        {
            "categoryName": "家居",
            "skuniCode": "70031_70031101_0",
            "productId": 70031,
            "productName": "毛毯",
            "skuList": [
                {
                    "skuniCode": "70031_70031101_0",
                    "name": "130*110cm"
                }
            ]
        },
        {
            "categoryName": "家居",
            "skuniCode": "70085_70085100_0",
            "productId": 70085,
            "productName": "拖鞋",
            "skuList": [
                {
                    "skuniCode": "70085_70085100_0",
                    "name": "36码"
                },
                {
                    "skuniCode": "70085_70085101_0",
                    "name": "38码"
                },
                {
                    "skuniCode": "70085_70085102_0",
                    "name": "40码"
                },
                {
                    "skuniCode": "70085_70085103_0",
                    "name": "42码"
                }
            ]
        },
        {
            "categoryName": "家居",
            "skuniCode": "70020_0_0",
            "productId": 70020,
            "productName": "脚垫",
            "skuList": [
                {
                    "skuniCode": "70020_0_0",
                    "name": "脚垫"
                }
            ]
        },
        {
            "categoryName": "家居",
            "skuniCode": "70100_70100100_0",
            "productId": 70100,
            "productName": "杯垫",
            "skuList": [
                {
                    "skuniCode": "70100_70100100_0",
                    "name": "杯垫圆x6件套"
                },
                {
                    "skuniCode": "70100_70100101_0",
                    "name": "杯垫方x6件套"
                }
            ]
        },
        {
            "categoryName": "家居",
            "skuniCode": "70030_70030103_0",
            "productId": 70030,
            "productName": "艺术餐盘",
            "skuList": [
                {
                    "skuniCode": "70030_70030103_0",
                    "name": "圆形"
                },
                {
                    "skuniCode": "70030_70030105_0",
                    "name": "方形"
                }
            ]
        },
        {
            "categoryName": "家居",
            "skuniCode": "70035_70035102_0",
            "productId": 70035,
            "productName": "马克杯 ",
            "skuList": [
                {
                    "skuniCode": "70035_70035102_0",
                    "name": "14oz"
                }
            ]
        },
        {
            "categoryName": "家居",
            "skuniCode": "70051_0_0",
            "productId": 70051,
            "productName": "围裙",
            "skuList": [
                {
                    "skuniCode": "70051_0_0",
                    "name": "围裙"
                }
            ]
        },
        {
            "categoryName": "装饰画",
            "skuniCode": "75001_75001101_0",
            "productId": 75001,
            "productName": "装饰画",
            "skuList": [
                {
                    "skuniCode": "75001_75001101_0",
                    "name": "方形"
                },
                {
                    "skuniCode": "75001_75001105_0",
                    "name": "竖形"
                },
                {
                    "skuniCode": "75001_75001108_0",
                    "name": "横形"
                }
            ]
        },
        {
            "categoryName": "装饰画",
            "skuniCode": "75021_75021101_0",
            "productId": 75021,
            "productName": "亚克力",
            "skuList": [
                {
                    "skuniCode": "75021_75021101_0",
                    "name": "方形"
                },
                {
                    "skuniCode": "75021_75021105_0",
                    "name": "竖形"
                },
                {
                    "skuniCode": "75021_75021122_0",
                    "name": "横形"
                }
            ]
        },
        {
            "categoryName": "装饰画",
            "skuniCode": "75051_75051101_0",
            "productId": 75051,
            "productName": "墙贴",
            "skuList": [
                {
                    "skuniCode": "75051_75051101_0",
                    "name": "高36cm "
                },
                {
                    "skuniCode": "75051_75051102_0",
                    "name": "高48cm"
                },
                {
                    "skuniCode": "75051_75051103_0",
                    "name": "高60cm"
                }
            ]
        },
        {
            "categoryName": "印刷品",
            "skuniCode": "88230_88230103_0",
            "productId": 88230,
            "productName": "Lomo卡片",
            "skuList": [
                {
                    "skuniCode": "88230_88230103_0",
                    "name": "10.2x7.6cm(8张)"
                }
            ]
        },
        {
            "categoryName": "印刷品",
            "skuniCode": "88240_88240100_0",
            "productId": 88240,
            "productName": "明信片",
            "skuList": [
                {
                    "skuniCode": "88240_88240100_0",
                    "name": "8张"
                }
            ]
        },
        {
            "categoryName": "娱乐",
            "skuniCode": "83201_0_0",
            "productId": 83201,
            "productName": "扑克牌",
            "skuList": [
                {
                    "skuniCode": "83201_0_0",
                    "name": "扑克牌"
                }
            ]
        },
        {
            "categoryName": "印刷品",
            "skuniCode": "88231_88231101_0",
            "productId": 88231,
            "productName": "贴纸",
            "skuList": [
                {
                    "skuniCode": "88231_88231101_0",
                    "name": "A4"
                }
            ]
        },
        {
            "categoryName": "印刷品",
            "skuniCode": "88232_88232101_0",
            "productId": 88232,
            "productName": "高清6寸照片8张",
            "skuList": [
                {
                    "skuniCode": "88232_88232101_0",
                    "name": "10张"
                }
            ]
        },
        {
            "categoryName": "印刷品",
            "skuniCode": "88233_0_0",
            "productId": 88233,
            "productName": "实木插台历",
            "skuList": [
                {
                    "skuniCode": "88233_0_0",
                    "name": "实木插台历"
                }
            ]
        }
    ]
}